the_utils/__init__.py
the_utils/bot.py
the_utils/common.py
the_utils/file.py
the_utils/logging.py
the_utils/plt.py
the_utils/save_load.py
the_utils/setting.py
the_utils/evaluation/__init__.py
the_utils/evaluation/unsupervised_graph_learning.py
the_utils-1.0.2.dist-info/METADATA
the_utils-1.0.2.dist-info/WHEEL
the_utils-1.0.2.dist-info/licenses/LICENSE
the_utils-1.0.2.dist-info/RECORD
