Metadata-Version: 2.4
Name: the_utils
Version: 1.0.2
Project-URL: Homepage, https://github.com/galogm/the_utils
Project-URL: Bug Tracker, https://github.com/galogm/the_utils/issues
Author-email: ming <gumingwork@gmail.com>
License: MIT License
License-File: LICENSE
Keywords: 
Classifier: License :: OSI Approved :: MIT License
Classifier: Programming Language :: Python :: 3
Classifier: Topic :: Software Development :: Libraries :: Python Modules
Requires-Python: >=3.8
Requires-Dist: matplotlib
Requires-Dist: munkres>=1.1.4
Requires-Dist: pytz>=2023.3.post1
Requires-Dist: scikit-learn
Requires-Dist: texttable>=1.6
Requires-Dist: torch>=1.12
Requires-Dist: torchaudio>=0.10.2
Requires-Dist: torchvision>=0.11.3
